chartlib/__init__.py
chartlib/advanced_charts.py
chartlib/animations.py
chartlib/core.py
chartlib/themes.py
ChartForgeTK-1.0.1.dist-info/LICENSE
ChartForgeTK-1.0.1.dist-info/METADATA
ChartForgeTK-1.0.1.dist-info/WHEEL
ChartForgeTK-1.0.1.dist-info/top_level.txt
ChartForgeTK-1.0.1.dist-info/RECORD
