Metadata-Version: 2.2
Name: ChartForgeTK
Version: 1.0.1
Summary: A modern, smooth, and dynamic charting library for Python using pure Tkinter
Home-page: https://github.com/ghassenTn/ChartForgeTK
Author: Ghassen
Author-email: ghassen.xr@gmail.com
Project-URL: Bug Reports, https://github.com/ghassenTn/ChartForgeTK/issues
Project-URL: Source, https://github.com/ghassenTn/ChartForgeTK
Project-URL: Documentation, https://github.com/ghassenTn/ChartForgeTK#readme
Keywords: chart,graph,visualization,tkinter,gui,plot,matplotlib alternative
Classifier: Development Status :: 5 - Production/Stable
Classifier: Intended Audience :: Developers
Classifier: License :: OSI Approved :: MIT License
Classifier: Programming Language :: Python :: 3
Classifier: Programming Language :: Python :: 3.8
Classifier: Programming Language :: Python :: 3.9
Classifier: Programming Language :: Python :: 3.10
Classifier: Programming Language :: Python :: 3.11
Classifier: Topic :: Scientific/Engineering :: Visualization
Classifier: Topic :: Software Development :: Libraries :: Python Modules
Classifier: Framework :: Matplotlib
Classifier: Operating System :: OS Independent
Requires-Python: >=3.8
License-File: LICENSE
Requires-Dist: typing; python_version < "3.5"
Dynamic: author
Dynamic: author-email
Dynamic: classifier
Dynamic: description
Dynamic: description-content-type
Dynamic: home-page
Dynamic: keywords
Dynamic: project-url
Dynamic: requires-dist
Dynamic: requires-python
Dynamic: summary
